Opytools/__init__.py
Opytools/modulo.py
Opytools/modulo2.py
Opytools-0.2.4.dist-info/METADATA
Opytools-0.2.4.dist-info/WHEEL
Opytools-0.2.4.dist-info/top_level.txt
Opytools-0.2.4.dist-info/RECORD
