Metadata-Version: 2.1
Name: Opytools
Version: 0.2.4
Summary: Libreria de herramientas para física computacional
Home-page: UNKNOWN
Author: Juan Esteban Ospina 
Author-email: juan.ospina25@udea.edu.co
License: MIT
Platform: UNKNOWN
Requires-Python: >=3.10.12
Requires-Dist: matplotlib (==3.8.0)
Requires-Dist: numpy (==1.26.1)
Requires-Dist: pandas (==2.1.1)
Requires-Dist: sympy (==1.12)
